unpaddedbase32/__init__.py
unpaddedbase32-0.2.0.dist-info/LICENSE
unpaddedbase32-0.2.0.dist-info/METADATA
unpaddedbase32-0.2.0.dist-info/WHEEL
unpaddedbase32-0.2.0.dist-info/top_level.txt
unpaddedbase32-0.2.0.dist-info/RECORD
