Metadata-Version: 2.1
Name: unpaddedbase32
Version: 0.2.0
Summary: Enables the ability to use base32 without padding
Home-page: https://github.com/beardog108/python-unpaddedbase32
Author: Kevin Froman
Author-email: beardog@mailbox.org
License: UNKNOWN
Platform: UNKNOWN
Classifier: Programming Language :: Python :: 3
Classifier: License :: OSI Approved :: GNU General Public License v3 (GPLv3)
Classifier: Operating System :: OS Independent
Requires-Python: >=3.6
